poetry_bundle_local_deps_plugin/__init__.py
poetry_bundle_local_deps_plugin/plugin.py
poetry_bundle_local_deps_plugin-0.2.1.dist-info/LICENSE
poetry_bundle_local_deps_plugin-0.2.1.dist-info/METADATA
poetry_bundle_local_deps_plugin-0.2.1.dist-info/WHEEL
poetry_bundle_local_deps_plugin-0.2.1.dist-info/entry_points.txt
poetry_bundle_local_deps_plugin-0.2.1.dist-info/RECORD
