Metadata-Version: 2.1
Name: poetry-bundle-local-deps-plugin
Version: 0.2.1
Summary: Poetry Plugin for Bundling Local Dependencies
Home-page: https://github.com/lucasvieirasilva/poetry-bundle-local-deps-plugin
License: MIT
Author: Lucas Vieira
Author-email: lucas.vieira94@outlook.com
Requires-Python: >=3.9,<4
Classifier: License :: OSI Approved :: MIT License
Classifier: Programming Language :: Python :: 3
Classifier: Programming Language :: Python :: 3.9
Classifier: Programming Language :: Python :: 3.10
Classifier: Programming Language :: Python :: 3.11
Classifier: Programming Language :: Python :: 3.12
Classifier: Programming Language :: Python :: 3.13
Project-URL: Repository, https://github.com/lucasvieirasilva/poetry-bundle-local-deps-plugin
